activity/__init__.py
activity/admin.py
activity/apps.py
activity/models.py
activity/tests.py
activity/views.py
buyer/__init__.py
buyer/admin.py
buyer/apps.py
buyer/models.py
buyer/tests.py
buyer/views.py
buyer/migrations/0001_initial.py
buyer/migrations/__init__.py
cart/__init__.py
cart/admin.py
cart/apps.py
cart/cart.py
cart/context_processors.py
cart/forms.py
cart/models.py
cart/tests.py
cart/urls.py
cart/views.py
cart/templates/cart/cart_detail.html
cart/templates/cart/cart_shortcuts.html
comment/__init__.py
comment/admin.py
comment/apps.py
comment/models.py
comment/tests.py
comment/views.py
comment/migrations/0001_initial.py
comment/migrations/__init__.py
image/__init__.py
image/admin.py
image/apps.py
image/models.py
image/tests.py
image/views.py
image/migrations/0001_initial.py
image/migrations/__init__.py
order/__init__.py
order/admin.py
order/apps.py
order/forms.py
order/models.py
order/tests.py
order/urls.py
order/views.py
order/api/__init__.py
order/api/apis.py
order/api/serializers.py
order/api/urls.py
order/migrations/0001_initial.py
order/migrations/__init__.py
order/templates/order/order_pdf.html
order/templates/order/ordercreate.html
order/templates/order/ordercreated.html
order/templates/order/orderlist.html
payment/__init__.py
payment/admin.py
payment/apps.py
payment/models.py
payment/tasks.py
payment/tests.py
payment/urls.py
payment/views.py
payment/templates/payment/payment_base.html
payment/templates/payment/payment_cancel.html
payment/templates/payment/payment_confirm.html
payment/templates/payment/payment_done.html
payment/templates/payment/payment_process.html
post/__init__.py
post/admin.py
post/apps.py
post/models.py
post/tests.py
post/views.py
product/__init__.py
product/admin.py
product/apps.py
product/models.py
product/tests.py
product/urls.py
product/views.py
product/api/__init__.py
product/api/apis.py
product/api/serializers.py
product/api/urls.py
product/migrations/0001_initial.py
product/migrations/__init__.py
shopsite-0.3.1.dist-info/METADATA
shopsite-0.3.1.dist-info/WHEEL
shopsite-0.3.1.dist-info/entry_points.txt
shopsite-0.3.1.dist-info/top_level.txt
shopsite-0.3.1.dist-info/RECORD
