Metadata-Version: 2.1
Name: shopsite
Version: 0.3.1
Summary: My Online Shoping Site on Django
Home-page: https://github.com/Godcrying123/
Author: zhkai
Author-email: jackson.zhang1@hotmail.com
License: MIT
Platform: UNKNOWN
Classifier: Development Status :: 3 - Alpha
Classifier: Intended Audience :: Developers
Classifier: Topic :: Software Development :: Libraries
Classifier: License :: OSI Approved :: MIT License
Classifier: Programming Language :: Python :: 3.7
Provides-Extra: ipython
Requires-Dist: ipython (==7.8.0) ; extra == 'ipython'
